{
  "current_level": "level_14",
  "exit": {
    "x": 9,
    "y": 5
  },
  "has_message": true,
  "knife_positions": [],
  "map": [
    [ 2, 2, 2, 0, 2, 1, 2, 0, 2, 1, 2 ],
    [ 1, 1, 1, 0, 1, 1, 2, 0, 2, 1, 2 ],
    [ 2, 2, 2, 0, 2, 2, 2, 0, 2, 1, 2 ],
    [ 0, 0, 0, 0, 0, 0, 0, 0, 0, 0, 0 ],
    [ 2, 1, 2, 0, 1, 1, 1, 0, 2, 2, 2 ],
    [ 1, 1, 2, 0, 1, 1, 1, 0, 2, 1, 1 ],
    [ 2, 1, 2, 0, 1, 1, 1, 0, 2, 2, 2 ],
    [ 0, 0, 0, 0, 0, 0, 0, 0, 0, 0, 0 ],
    [ 2, 1, 2, 0, 2, 2, 2, 0, 2, 1, 2 ],
    [ 2, 1, 1, 0, 1, 1, 2, 0, 1, 1, 1 ],
    [ 2, 2, 2, 0, 2, 2, 2, 0, 2, 2, 2 ]
  ],
  "map_size": {
    "x": 11,
    "y": 11
  },
  "message_location": {
    "x": 1,
    "y": 5
  },
  "message_text": "I had a most nerve-racking series of events.\nI was trying different combinations of the material found here but I quickly realized that I had blocked off any possibility of progressing to the next gateway.\nIn my panic, I slipped on the smooth tile causing me to fall down into the abyss.\nI closed my eyes, bracing for whatever was about to come, but it never came.\nUpon opening my eyes, it revealed that everything, including myself, had been put back in its original place when I first entered this area.\nUnsure what to make of this, but I am now able to continue onwards.",
  "name": "level_14",
  "next_level": "level_15",
  "number_of_knives": 0,
  "number_of_orbs": 6,
  "orb_positions": [
    {
      "x": 1,
      "y": 1
    },
    {
      "x": 5,
      "y": 1
    },
    {
      "x": 9,
      "y": 1
    },
    {
      "x": 5,
      "y": 9
    },
    {
      "x": 1,
      "y": 9
    },
    {
      "x": 9,
      "y": 9
    }
  ],
  "spawn": {
    "x": 5,
    "y": 5
  }
}